bfade/__init__.py
bfade/abstract.py
bfade/dataset.py
bfade/elhaddad.py
bfade/statistics.py
bfade/util.py
bfade/viewers.py
b_fade-0.0.0.dist-info/LICENSE
b_fade-0.0.0.dist-info/METADATA
b_fade-0.0.0.dist-info/WHEEL
b_fade-0.0.0.dist-info/top_level.txt
b_fade-0.0.0.dist-info/RECORD
