Metadata-Version: 2.1
Name: b-fade
Version: 0.0.0
Summary: B-FADE: Bayesian FAtigue moDel Estimator
Home-page: https://github.com/aletgn/b-fade
Author: Alessandro Tognan
Author-email: tognan.alessandro@spes.uniud.it
Project-URL: Bug Tracker, https://github.com/aletgn/b-fade/issues
Classifier: Programming Language :: Python :: 3
Classifier: License :: OSI Approved :: GNU General Public License v3 (GPLv3)
Classifier: Operating System :: OS Independent
Requires-Python: >=3.6
License-File: LICENSE
Requires-Dist: numpy
Requires-Dist: scipy
Requires-Dist: matplotlib
Requires-Dist: pandas
Requires-Dist: odfpy
Requires-Dist: openpyxl
Requires-Dist: scikit-learn
Requires-Dist: numdifftools
Requires-Dist: PyYAML
Provides-Extra: dev
Requires-Dist: pytest ; extra == 'dev'
Requires-Dist: twine ; extra == 'dev'
Requires-Dist: setuptools ; extra == 'dev'
Requires-Dist: build ; extra == 'dev'
Provides-Extra: test
Requires-Dist: notebook ; extra == 'test'
